{
  "link": "supportedemployment",
  "title": "null",
  "autoCrawledTitle": "Supported Employment Program | Global Diversity and Inclusion",
  "keywords": "null",
  "category": "null",
  "url": "https://nam06.safelinks.protection.outlook.com/?url=https%3A%2F%2Fwww.microsoft.com%2Fen-us%2Fdiversity%2Fsupportedemployment&data=05%7C01%7Cv-gimagu%40microsoft.com%7Cd53f057459384a9c660908da44119a87%7C72f988bf86f141af91ab2d7cd011db47%7C1%7C0%7C637897139673229910%7CUnknown%7CTWFpbGZsb3d8eyJWIjoiMC4wLjAwMDAiLCJQIjoiV2luMzIiLCJBTiI6Ik1haWwiLCJXVCI6Mn0%3D%7C3000%7C%7C%7C&sdata=e8hb9Xv7K8bBVJCDDQLT3XLet1VxIpfL6e%2BzHyUVdoQ%3D&reserved=0"
}
